mockupgen/__init__.py
mockupgen/__main__.py
mockupgen/helpers.py
mockupgen/image_processing.py
mockupgen/mockupgen.py
mockupgen-1.5.1.dist-info/LICENSE.md
mockupgen-1.5.1.dist-info/METADATA
mockupgen-1.5.1.dist-info/WHEEL
mockupgen-1.5.1.dist-info/entry_points.txt
mockupgen-1.5.1.dist-info/top_level.txt
mockupgen-1.5.1.dist-info/RECORD
