Metadata-Version: 2.1
Name: mockupgen
Version: 1.5.1
Summary: A tool that generates a 3D device mockup from a screenshot.
Home-page: https://github.com/rmenon1008/mockupgen
Author: Rohan Menon
License-File: LICENSE.md
Requires-Dist: opencv-python
Requires-Dist: numpy
Requires-Dist: colorama
